flask_wire/__init__.py
flask_wire/utils.py
flask_wire/static/js/bundle.js
flask_wire/templates/wire/macros.html
Flask_Wire-1.0.4.dist-info/METADATA
Flask_Wire-1.0.4.dist-info/WHEEL
Flask_Wire-1.0.4.dist-info/top_level.txt
Flask_Wire-1.0.4.dist-info/RECORD
